Workbook

Sheet Financial Model DDM (4)
C3: DDM P0=D1/(r-g)
C4: Re = Rf + b x (Rm-Rf)
C5: CAPM | E5: Sumber
C6: Risk Free Rate | D6: 0.07 | E6: SBN indonesia (BenchMark)
C7: Beta | D7: 0.76 | E7: Damodaran
C8: Equity Risk Premium (Rm-Rf) | D8: 0.0669 | E8: Damodaran
B9: r = Rf + b x ERP | C9: Cost Of Equity | D9: =D6+D7*D8 -> 0.120844
C11: Input(Asumsi) | D11: 2023 | E11: 2024 | F11: 2025 | G11: 2026 | H11: 2027 | I11: 2028 | J11: 2029 | K11: 2030 | L11: 2026 dibangun dari data aktual (baris 113-123). 2027-2030 tumbuh dari pendapatan dan mewarisi rasio 2026.
B12: Pertumbuhan = Pendapatan_t / Pendapatan_t-1 - 1 | C12: Pertumbuhan Pendapatan | E12: =E23/D23-1 -> 0.05121491 | F12: =F23/E23-1 -> 0.072881235 | G12: =G23/F23-1 -> -0.11026109 | H12: 0.06 | I12: =H12 -> 0.06 | J12: =I12 -> 0.06 | K12: =J12 -> 0.06 | L12: 2026 = hasil hitungan, bukan input. H12 satu-satunya input pertumbuhan; 2028-2030 mengikutinya.
B13: HPP% = BPP / Pendapatan | C13: HPP (% Pendapatan) | D13: =D24/D23 -> -0.3299263 | E13: =E24/E23 -> -0.32179998 | F13: =F24/F23 -> -0.35281851 | G13: =G24/G23 -> -0.34142287 | H13: =G13 -> -0.34142287 | I13: =H13 -> -0.34142287 | J13: =I13 -> -0.34142287 | K13: =J13 -> -0.34142287 | L13: 2026 = hasil build-up. 2027-2030 mewarisi rasio 2026.
B14: Beban Usaha% = Beban Usaha / Pendapatan | C14: Beban Usaha(%Pendapatan) | D14: =D26/D23 -> -0.15976372 | E14: =E26/E23 -> -0.18352335 | F14: =F26/F23 -> -0.18458685 | G14: =G26/G23 -> -0.1262894 | H14: =G14 -> -0.1262894 | I14: =H14 -> -0.1262894 | J14: =I14 -> -0.1262894 | K14: =J14 -> -0.1262894 | L14: 2026 = hasil build-up (12,6%). 2027-2030 mewarisi rasio 2026.
B15: = Penghasilan/Beban Lain-lain (baris 28) | C15: Penghasilan/Beban Lain-lain | D15: =D28 -> 43 | E15: =E28 -> 344 | F15: =F28 -> 107 | G15: =G28 -> -44 | H15: =G15 -> -44 | I15: =H15 -> -44 | J15: =I15 -> -44 | K15: =J15 -> -44
B16: Tarif Pajak = Beban Pajak / Laba Sebelum Pajak | C16: Beban Pajak Penghasilan (Tax Rate) | D16: 0.19 | L16: Pakai 19% (tarif khusus perseroan terbuka, bukan 22%). Bukti: tarif efektif aktual 19,6% / 19,9% / 19,7% / 19,0% - lihat baris 102.
B18: Hak Minoritas% = Hak Minoritas / Laba Bersih | C18: Hak Minoritas (% Laba Bersih) | D18: =D34/D31 -> 0.083112688 | E18: =E34/E31 -> 0.088006409 | F18: =F34/F31 -> 0.082367516 | G18: 0.038407 | H18: =G18 -> 0.038407 | I18: =H18 -> 0.038407 | J18: =I18 -> 0.038407 | K18: =J18 -> 0.038407 | L18: Historis = hak minoritas / laba bersih. 2026 = 3,84% (lapkeu interim Q2 2026) setelah dekonsolidasi BSI; wajar dipatok datar 2027-2030 karena BSI permanen keluar konsolidasi. | M18: Sumber: Laporan Keuangan Interim BMRI Q2 2026 (bankmandiri.co.id). Turun dari ~8,2% karena DEKONSOLIDASI BSI (efektif 1 Feb 2026, surat OJK No. CRL.CSC/CMA.290/2026 tgl 27 Jan 2026). BSI dimiliki 51,47% = penyumbang hak minoritas terbesar, kini keluar dari konsolidasi. Jadi penurunan ini STRUKTURAL, bukan anomali satu semester.
B19: DPR = Dividen / Laba Atribusi | C19: Payout Ratio / DPR (2026-2030) | D19: 0.7
C20: Laporan Laba Rugi
C21: Periode | G21: 1 | H21: =G21+1 -> 2 | I21: =H21+1 -> 3 | J21: =I21+1 -> 4 | K21: =J21+1 -> 5 | L21: Penghitung tahun t=1..5 untuk faktor diskonto (baris 60).
C22: Dalam Miliar Rupiah IDR | D22: 2023 | E22: 2024 | F22: 2025 | G22: 2026 | H22: 2027 | I22: 2028 | J22: 2029 | K22: 2030
B23: 2026 = build-up (baris 113); 2027-2030 = tahun lalu x (1+g) | C23: Pendapatan | D23: 146266 | E23: 153757 | F23: 164963 | G23: =F113 -> 146774 | H23: =G23*(1+H12) -> 155580.44 | I23: =H23*(1+I12) -> 164915.27 | J23: =I23*(1+J12) -> 174810.18 | K23: =J23*(1+K12) -> 185298.79
B24: = HPP% (baris 13) x Pendapatan | C24: Beban Pokok Penjualan | D24: -48257 | E24: -49479 | F24: -58202 | G24: =F114 -> -50112 | H24: =H13*H23 -> -53118.72 | I24: =I13*I23 -> -56305.843 | J24: =J13*J23 -> -59684.194 | K24: =K13*K23 -> -63265.245
B25: Laba Kotor = Pendapatan - BPP | C25: Laba Kotor | D25: =D23+D24 -> 98009 | E25: =E23+E24 -> 104278 | F25: =F23+F24 -> 106761 | G25: =G23+G24 -> 96662 | H25: =H23+H24 -> 102461.72 | I25: =I23+I24 -> 108609.42 | J25: =J23+J24 -> 115125.99 | K25: =K23+K24 -> 122033.55
B26: = Beban Usaha% (baris 14) x Pendapatan | C26: Beban Usaha | D26: -23368 | E26: -28218 | F26: -30450 | G26: =F116 -> -18536 | H26: =H14*H23 -> -19648.16 | I26: =I14*I23 -> -20827.05 | J26: =J14*J23 -> -22076.673 | K26: =K14*K23 -> -23401.273 | L26: 2027-2030 = rasio baris 14 x pendapatan.
B27: Laba Usaha = Laba Kotor - Beban Usaha | C27: Laba Usaha | D27: =D25+D26 -> 74641 | E27: =E25+E26 -> 76060 | F27: =F25+F26 -> 76311 | G27: =G25+G26 -> 78126 | H27: =H25+H26 -> 82813.56 | I27: =I25+I26 -> 87782.374 | J27: =J25+J26 -> 93049.316 | K27: =K25+K26 -> 98632.275
C28: Penghasilan/ Beban Lain lain | D28: 43 | E28: 344 | F28: 107 | G28: =F118 -> -44 | H28: =H15 -> -44 | I28: =I15 -> -44 | J28: =J15 -> -44 | K28: =K15 -> -44
B29: Laba Sebelum Pajak = Laba Usaha + Lain-lain | C29: Laba Sebelum Pajak | D29: =D27+D28 -> 74684 | E29: =E27+E28 -> 76404 | F29: =F27+F28 -> 76418 | G29: =G27+G28 -> 78082 | H29: =H27+H28 -> 82769.56 | I29: =I27+I28 -> 87738.374 | J29: =J27+J28 -> 93005.316 | K29: =K27+K28 -> 98588.275
B30: = -Tarif Pajak (D16) x Laba Sebelum Pajak | C30: Beban Pajak Penghasilan | D30: -14633 | E30: -15238 | F30: -15071 | G30: =F120 -> -14832.79 | H30: =IF(H29>0,-$D$16*H29,0) -> -15726.216 | I30: =IF(I29>0,-$D$16*I29,0) -> -16670.291 | J30: =IF(J29>0,-$D$16*J29,0) -> -17671.01 | K30: =IF(K29>0,-$D$16*K29,0) -> -18731.772 | L30: 2026 = pajak H1 aktual + H2 pada tarif 19%. 2027-2030 tarif 19% penuh.
B31: Laba Bersih = Laba Sebelum Pajak - Pajak | C31: Laba Bersih Tahun Berjalan | D31: =D29+D30 -> 60051 | E31: =E29+E30 -> 61166 | F31: =F29+F30 -> 61347 | G31: =G29+G30 -> 63249.21 | H31: =H29+H30 -> 67043.344 | I31: =I29+I30 -> 71068.083 | J31: =J29+J30 -> 75334.306 | K31: =K29+K30 -> 79856.503
C32: Pendapatan Komprehensif Lain | D32: 906 | E32: -18 | F32: 7128 | G32: =F122 -> -3655 | H32: 0 | I32: =H32 -> 0 | J32: =I32 -> 0 | K32: =J32 -> 0 | L32: H1 2026 aktual -3.655; 2027-2030 diasumsikan 0.
B33: Laba Komprehensif = Laba Bersih + OCI | C33: Jumlah Laba Komprehensif | D33: =D31+D32 -> 60957 | E33: =E31+E32 -> 61148 | F33: =F31+F32 -> 68475 | G33: =G31+G32 -> 59594.21 | H33: =H31+H32 -> 67043.344 | I33: =I31+I32 -> 71068.083 | J33: =J31+J32 -> 75334.306 | K33: =K31+K32 -> 79856.503
B34: = Hak Minoritas% x Laba Bersih | C34: Hak Minoritas (Non-Controlling Interest) | D34: =D31-D35 -> 4991 | E34: =E31-E35 -> 5383 | F34: =F31-F35 -> 5053 | G34: =G18*G31 -> 2429.2124 | H34: =H18*H31 -> 2574.9337 | I34: =I18*I31 -> 2729.5118 | J34: =J18*J31 -> 2893.3647 | K34: =K18*K31 -> 3067.0487 | L34: Historis = baris 31 - baris 35 (selisih rekonsiliasi), bukan angka laporan.
B35: Laba Atribusi = Laba Bersih - Hak Minoritas | C35: Laba Bersih Yang Dapat Diatribusikan | D35: 55060 | E35: 55783 | F35: 56294 | G35: =G31-G34 -> 60819.998 | H35: =H31-H34 -> 64468.41 | I35: =I31-I34 -> 68338.571 | J35: =J31-J34 -> 72440.941 | K35: =K31-K34 -> 76789.454 | L35: = EPS Stockbit x 93,33 miliar lembar. Baris Hak Minoritas & Laba Atribusi di Stockbit kosong - jangan dipakai.
C37: Jumlah Saham Beredar (miliar lembar) | D37: 93.33 | E37: =$D$37 -> 93.33 | F37: =$D$37 -> 93.33 | G37: =$D$37 -> 93.33 | H37: =$D$37 -> 93.33 | I37: =$D$37 -> 93.33 | J37: =$D$37 -> 93.33 | K37: =$D$37 -> 93.33
C38: Tahun | D38: =D22 -> 2023 | E38: =E22 -> 2024 | F38: =F22 -> 2025 | G38: =G22 -> 2026 | H38: =H22 -> 2027 | I38: =I22 -> 2028 | J38: =J22 -> 2029 | K38: =K22 -> 2030
B39: EPS = Laba Atribusi / Lembar Beredar | C39: EPS (Laba Diatribusikan / Lembar Beredar) | D39: =D35/$D$37 -> 589.94964 | E39: =E35/$D$37 -> 597.69635 | F39: =F35/$D$37 -> 603.17154 | G39: =G35/$D$37 -> 651.66611 | H39: =H35/$D$37 -> 690.75763 | I39: =I35/$D$37 -> 732.22512 | J39: =J35/$D$37 -> 776.18066 | K39: =K35/$D$37 -> 822.77354 | L39: EPS jadi dasar hitungan dividen.
B40: DPS = DPR x EPS | C40: Dividen | D40: =D41*D39 -> 353.96978 | E40: =E41*E39 -> 466.20315 | F40: =F41*F39 -> 476.50552 | G40: =G41*G39 -> 456.16627 | H40: =H41*H39 -> 483.53034 | I40: =I41*I39 -> 512.55759 | J40: =J41*J39 -> 543.32646 | K40: =K41*K39 -> 575.94147 | L40: 2026-2030 = DPR x EPS. 2023-2025 sesuai DPS aktual.
B41: 2026-2030 = asumsi DPR (D19) | C41: Payout Ratio / DPR | D41: 0.6 | E41: 0.78 | F41: 0.79 | G41: =$D$19 -> 0.7 | H41: =$D$19 -> 0.7 | I41: =$D$19 -> 0.7 | J41: =$D$19 -> 0.7 | K41: =$D$19 -> 0.7 | L41: 2023-2025 = DPR aktual. 2026-2030 mengikuti D19.
B42: RE = Laba Atribusi - (DPS x lembar) | C42: Laba Ditahan (Laba Atribusi - Total Dividen) | D42: =D35-D40*$D$37 -> 22024 | E42: =E35-E40*$D$37 -> 12272.26 | F42: =F35-F40*$D$37 -> 11821.74 | G42: =G35-G40*$D$37 -> 18245.999 | H42: =H35-H40*$D$37 -> 19340.523 | I42: =I35-I40*$D$37 -> 20501.571 | J42: =J35-J40*$D$37 -> 21732.282 | K42: =K35-K40*$D$37 -> 23036.836 | L42: Laba yang tidak dibagikan; menambah ekuitas tahun itu.
B43: Ekuitas_t = Ekuitas_t-1 + RE_t + OCI_t | C43: Ekuitas Atribusi (akhir tahun) | D43: =E43-E42-E32 -> 262546.67 | E43: =F43-F42-F32 -> 274800.93 | F43: 293750.67 | G43: =F43+G42+G32 -> 308341.67 | H43: =G43+H42+H32 -> 327682.19 | I43: =H43+I42+I32 -> 348183.76 | J43: =I43+J42+J32 -> 369916.04 | K43: =J43+K42+K32 -> 392952.88
B44: BVPS = Ekuitas / lembar beredar | C44: BVPS (Ekuitas / Lembar Beredar) | D44: =D43/$D$37 -> 2813.1005 | E44: =E43/$D$37 -> 2944.4008 | F44: =F43/$D$37 -> 3147.441 | G44: =G43/$D$37 -> 3303.7787 | H44: =H43/$D$37 -> 3511.006 | I44: =I43/$D$37 -> 3730.6736 | J44: =J43/$D$37 -> 3963.5277 | K44: =K43/$D$37 -> 4210.3598
B45: ROE = Laba Atribusi / Ekuitas | C45: ROE (Laba Atribusi / Ekuitas) | D45: =D35/D43 -> 0.2097151 | E45: =E35/E43 -> 0.20299422 | F45: =F35/F43 -> 0.19163871 | G45: =G35/G43 -> 0.19724871 | H45: =H35/H43 -> 0.19674066 | I45: =I35/I43 -> 0.19627156 | J45: =J35/J43 -> 0.19583076 | K45: =K35/K43 -> 0.19541644
B46: Bagian laba yang TIDAK dibagikan = 1 - DPR | C46: Laba yang Ditahan / Retention Ratio (1 - DPR) | D46: =1-D41 -> 0.4 | E46: =1-E41 -> 0.22 | F46: =1-F41 -> 0.21 | G46: =1-G41 -> 0.3 | H46: =1-H41 -> 0.3 | I46: =1-I41 -> 0.3 | J46: =1-J41 -> 0.3 | K46: =1-K41 -> 0.3
B47: SGR = ROE x (1-DPR). Pertumbuhan maksimum tanpa cari modal baru | C47: Batas Pertumbuhan yang Bisa Didanai Sendiri (SGR) | D47: =D45*D46 -> 0.083886039 | E47: =E45*E46 -> 0.044658728 | F47: =F45*F46 -> 0.04024413 | G47: =G45*G46 -> 0.059174614 | H47: =H45*H46 -> 0.059022197 | I47: =I45*I46 -> 0.058881468 | J47: =J45*J46 -> 0.058749229 | K47: =K45*K46 -> 0.058624933
C49: Gordon Growth Model
B50: ROE terminal = ROE kolom 2030 (K45) | C50: ROE Terminal (2030) | D50: =K45 -> 0.19541644
B51: Bagian laba yang tidak dibagikan di 2030 = 1 - DPR (K46) | C51: Laba yang Ditahan Terminal (2030) | D51: =K46 -> 0.3
B52: SGR terminal = ROE x (1-DPR) tahun 2030 (K47) | C52: Batas Pertumbuhan Terminal (SGR = ROE x Laba Ditahan) | D52: =K47 -> 0.058624933
B53: g = asumsi; syarat g < SGR dan g < r | C53: g Terminal (perpetuitas) | D53: 0.05
B54: D1 = dividen dari laba 2026 | C54: Dividen berikutnya (D1) | D54: =G40 -> 456.16627
B55: P0 = D1/(r-g) | C55: Nilai Wajar (DDM) | D55: =D54/($D$9-$D$53) -> 6439.0248
C56: Cek Konsistensi: g < SGR Terminal DAN g < r? | D56: =IF(AND($D$53<$D$52,$D$53<$D$9),"OK","LANGGAR") -> OK
C57: DDM Dua Tahap
B58: t = jumlah tahun dari 2025 (1 s.d. 5) | C58: Tahun | D58: =G38 -> 2026 | E58: =H38 -> 2027 | F58: =I38 -> 2028 | G58: =J38 -> 2029 | H58: =K38 -> 2030
B59: Dividen = DPR x EPS tahun itu | C59: Dividen per Saham | D59: =G40 -> 456.16627 | E59: =H40 -> 483.53034 | F59: =I40 -> 512.55759 | G59: =J40 -> 543.32646 | H59: =K40 -> 575.94147
B60: Faktor Diskonto = 1 / (1+r) pangkat t | C60: Faktor Diskonto @ r | D60: =1/(1+$D$9)^G$21 -> 0.89218482 | E60: =1/(1+$D$9)^H$21 -> 0.79599375 | F60: =1/(1+$D$9)^I$21 -> 0.71017354 | G60: =1/(1+$D$9)^J$21 -> 0.63360605 | H60: =1/(1+$D$9)^K$21 -> 0.5652937
B61: Nilai sekarang = Dividen x Faktor Diskonto | C61: Nilai Sekarang Dividen (PV) | D61: =D59*D60 -> 406.98462 | E61: =E59*E60 -> 384.88713 | F61: =F59*F60 -> 364.00483 | G61: =G59*G60 -> 344.25493 | H61: =H59*H60 -> 325.57609
B62: Tahap 1 = jumlah nilai sekarang dividen 2026 s.d. 2030 | C62: Nilai Sekarang Dividen 2026-2030 (Tahap 1) | D62: =SUM(D61:H61) -> 1825.7076
B63: Dividen tahun pertama setelah periode proyeksi | C63: Dividen 2031 (= dividen 2030 x (1+g)) | D63: =H59*(1+$D$53) -> 604.73855
B64: Terminal Value = Dividen 2031 / (r - g) | C64: Terminal Value akhir 2030 | D64: =D63/($D$9-$D$53) -> 8536.1999
B65: Tahap 2 = Terminal Value x Faktor Diskonto kolom 2030 | C65: Nilai Sekarang Terminal Value (Tahap 2) | D65: =D64*H60 -> 4825.46
B66: Nilai Wajar = Tahap 1 + Tahap 2 | C66: Nilai Wajar (DDM Dua Tahap) | D66: =D62+D65 -> 6651.1676
B67: Porsi = Tahap 2 / Nilai Wajar | C67: Porsi Nilai yang Berasal dari Terminal Value | D67: =D65/D66 -> 0.7255057
C69: Valuasi Relatif (Pembanding Bank Lain) | D69: P/BV | E69: P/E
C70: BBCA | D70: 2.95 | E70: 13.36
C71: BBRI | D71: 1.43 | E71: 7.78
C72: BBNI | D72: 0.86 | E72: 6.38
B73: Rata-rata = AVERAGE(BBCA, BBRI, BBNI) | C73: Rata-rata Bank Pembanding | D73: =AVERAGE(D70:D72) -> 1.7466667 | E73: =AVERAGE(E70:E72) -> 9.1733333
C74: Nilai Buku per Saham (BVPS) | D74: 3049.2 | E74: =F39 -> 603.17154 | F74: EPS
B75: Nilai Wajar = Multiple rata-rata x BVPS (atau EPS) | C75: Nilai Wajar BMRI | D75: =D73*D74 -> 5325.936 | E75: =E73*E74 -> 5533.0936
C77: Ringkasan (Nilai Wajar BMRI) | E77: Bobot
C78: Pendekatan Pendapatan - DDM Dua Tahap | D78: =D66 -> 6651.1676 | E78: 0.2
C79: Pendekatan Pasar - P/BV Bank Pembanding | D79: =D75 -> 5325.936 | E79: 0.6
C80: Pendekatan Pasar - P/E Bank Pembanding | D80: =E75 -> 5533.0936 | E80: 0.2
B81: Gabungan = jumlah (nilai x bobot) | C81: Nilai Wajar BMRI (Gabungan 3 Metode) | D81: =SUMPRODUCT(D78:D80,E78:E80) -> 5632.4138 | E81: =SUM(E78:E80) -> 1
C82: Harga Pasar Sekarang | D82: 4200
B83: Upside = Nilai Wajar / Harga Pasar - 1 | C83: Potensi Kenaikan (Upside) | D83: =D81/D82-1 -> 0.34105092
C84: Data Aktual Kuartal
C85: Dalam Miliar Rupiah IDR | D85: Q1 2025 | E85: Q2 2025 | F85: Q3 2025 | G85: Q4 2025 | H85: Q1 2026 | I85: Q2 2026 | J85: H1 2025 | K85: H1 2026 | L85: FY2025
C86: Pendapatan | D86: 40055 | E86: 41583 | F86: 40960 | G86: 42365 | H86: 37662 | I86: 35725 | J86: =D86+E86 -> 81638 | K86: =H86+I86 -> 73387 | L86: =SUM(D86:G86) -> 164963
C87: Beban Pokok Penjualan | D87: -14121 | E87: -15071 | F87: -14846 | G87: -14164 | H87: -12325 | I87: -12731 | J87: =D87+E87 -> -29192 | K87: =H87+I87 -> -25056 | L87: =SUM(D87:G87) -> -58202
B88: Laba Kotor = Pendapatan - BPP | C88: Laba Kotor | D88: =D86+D87 -> 25934 | E88: =E86+E87 -> 26512 | F88: =F86+F87 -> 26114 | G88: =G86+G87 -> 28201 | H88: =H86+H87 -> 25337 | I88: =I86+I87 -> 22994 | J88: =D88+E88 -> 52446 | K88: =H88+I88 -> 48331 | L88: =SUM(D88:G88) -> 106761
C89: Beban Usaha | D89: -7819 | E89: -11182 | F89: -8123 | G89: -3325 | H89: -5415 | I89: -3853 | J89: =D89+E89 -> -19001 | K89: =H89+I89 -> -9268 | L89: =SUM(D89:G89) -> -30449
B90: Laba Usaha = Laba Kotor - Beban Usaha | C90: Laba Usaha | D90: =D88+D89 -> 18115 | E90: =E88+E89 -> 15330 | F90: =F88+F89 -> 17991 | G90: =G88+G89 -> 24876 | H90: =H88+H89 -> 19922 | I90: =I88+I89 -> 19141 | J90: =D90+E90 -> 33445 | K90: =H90+I90 -> 39063 | L90: =SUM(D90:G90) -> 76312
C91: Penghasilan/Beban Lain-lain | D91: 65 | E91: 16 | F91: 33 | G91: -7 | H91: 22 | I91: -44 | J91: =D91+E91 -> 81 | K91: =H91+I91 -> -22 | L91: =SUM(D91:G91) -> 107
B92: Laba Sebelum Pajak = Laba Usaha + Lain-lain | C92: Laba Sebelum Pajak | D92: =D90+D91 -> 18180 | E92: =E90+E91 -> 15346 | F92: =F90+F91 -> 18024 | G92: =G90+G91 -> 24869 | H92: =H90+H91 -> 19944 | I92: =I90+I91 -> 19097 | J92: =D92+E92 -> 33526 | K92: =H92+I92 -> 39041 | L92: =SUM(D92:G92) -> 76419
C93: Beban Pajak Penghasilan | D93: -3649 | E93: -3025 | F93: -3501 | G93: -4897 | H93: -3731 | I93: -3684 | J93: =D93+E93 -> -6674 | K93: =H93+I93 -> -7415 | L93: =SUM(D93:G93) -> -15072
B94: Laba Bersih = Laba Sebelum Pajak - Pajak | C94: Laba Bersih Tahun Berjalan | D94: =D92+D93 -> 14531 | E94: =E92+E93 -> 12321 | F94: =F92+F93 -> 14523 | G94: =G92+G93 -> 19972 | H94: =H92+H93 -> 16213 | I94: =I92+I93 -> 15413 | J94: =D94+E94 -> 26852 | K94: =H94+I94 -> 31626 | L94: =SUM(D94:G94) -> 61347
C95: Pendapatan Komprehensif Lain | D95: 683 | E95: 1478 | F95: 1648 | G95: 3318 | H95: -2881 | I95: -774 | J95: =D95+E95 -> 2161 | K95: =H95+I95 -> -3655 | L95: =SUM(D95:G95) -> 7127
B96: Laba Komprehensif = Laba Bersih + OCI | C96: Jumlah Laba Komprehensif | D96: =D94+D95 -> 15214 | E96: =E94+E95 -> 13799 | F96: =F94+F95 -> 16171 | G96: =G94+G95 -> 23290 | H96: =H94+H95 -> 13332 | I96: =I94+I95 -> 14639 | J96: =D96+E96 -> 29013 | K96: =H96+I96 -> 27971 | L96: =SUM(D96:G96) -> 68474
C98: Rasio Kunci (Diagnostik)
B99: = BPP / Pendapatan | C99: BPP % Pendapatan | D99: =D87/D86 -> -0.35254026 | E99: =E87/E86 -> -0.36243176 | F99: =F87/F86 -> -0.36245117 | G99: =G87/G86 -> -0.33433259 | H99: =H87/H86 -> -0.32725293 | I99: =I87/I86 -> -0.35636109 | J99: =J87/J86 -> -0.35757858 | K99: =K87/K86 -> -0.34142287 | L99: =L87/L86 -> -0.35281851 | M99: Fungsi: ukur beban bunga/dana per rupiah pendapatan. HIDUP - jadi asumsi BPP H2 2026 (D106).
B100: = Beban Usaha / Pendapatan | C100: Beban Usaha % Pendapatan | D100: =D89/D86 -> -0.19520659 | E100: =E89/E86 -> -0.26890797 | F100: =F89/F86 -> -0.19831543 | G100: =G89/G86 -> -0.078484598 | H100: =H89/H86 -> -0.14377888 | I100: =I89/I86 -> -0.10785164 | J100: =J89/J86 -> -0.23274701 | K100: =K89/K86 -> -0.1262894 | L100: =L89/L86 -> -0.18458078 | M100: Fungsi: ukur efisiensi beban operasional. Diagnostik. H1 2026 = 9.268 vs H1 2025 = 19.001 (-51,2%), sumber kenaikan laba meski pendapatan turun 10,1%.
B101: = Beban Usaha / Laba Kotor | C101: Rasio Beban thd Laba Kotor (Cost-to-Income) | D101: =-D89/D88 -> 0.30149611 | E101: =-E89/E88 -> 0.42177127 | F101: =-F89/F88 -> 0.3110592 | G101: =-G89/G88 -> 0.11790362 | H101: =-H89/H88 -> 0.21371907 | I101: =-I89/I88 -> 0.16756545 | J101: =-J89/J88 -> 0.36229646 | K101: =-K89/K88 -> 0.19176098 | L101: =-L89/L88 -> 0.28520714 | M101: Fungsi: ukur porsi laba kotor yang habis untuk beban usaha; pembanding antarbank. Diagnostik.
B102: = Beban Pajak / Laba Sebelum Pajak | C102: Tarif Pajak Efektif | D102: =-D93/D92 -> 0.20071507 | E102: =-E93/E92 -> 0.19711977 | F102: =-F93/F92 -> 0.19424101 | G102: =-G93/G92 -> 0.19691182 | H102: =-H93/H92 -> 0.18707381 | I102: =-I93/I92 -> 0.19290988 | J102: =-J93/J92 -> 0.19906938 | K102: =-K93/K92 -> 0.18992854 | L102: =-L93/L92 -> 0.19722844 | M102: Fungsi: cek tarif pajak yang benar-benar dibayar. Diagnostik - jadi bukti D16 dipatok 19%, bukan 22%.
C104: Asumsi H2 2026 & Beban Usaha
C105: Pertumbuhan Pendapatan H2 vs H1 2026 | D105: 0 | E105: Input. 0% = H2 sama dengan H1.
C106: BPP % Pendapatan (H2 2026 dst) | D106: =K99 -> -0.34142287 | E106: ="Mengikuti realisasi H1 2026 (K99) = "&TEXT(K99,"0.0%")&", bukan rata-rata 3 tahun." -> Mengikuti realisasi H1 2026 (K99) = -34.1%, bukan rata-rata 3 tahun.
C107: Pertumbuhan Beban Usaha H2 vs H1 2026 | D107: 0 | E107: Input. 0% = beban usaha H2 sama dengan H1 aktual.
C109: Penghasilan/Beban Lain-lain per Semester | D109: =K91 -> -22 | E109: Mengikuti realisasi H1 2026. Kecil dan volatil.
C111: Susunan FY2026 dari Data Aktual (bukan dari asumsi pendapatan)
C112: Dalam Miliar Rupiah IDR | D112: H1 2026 Aktual | E112: H2 2026 Proyeksi | F112: FY2026
...

Sheet Summary DDM (4)
B2: VALUASI SAHAM BMRI - DIVIDEND DISCOUNT MODEL
B3: PT Bank Mandiri (Persero) Tbk | Basis: Financial Model DDM (4) - dijangkarkan ke data aktual H1 2026 | Angka dalam Rupiah per saham kecuali dinyatakan lain
B5: 1. KESIMPULAN | I5: 8
B6: Harga Pasar Saat Ini | C6: ='Financial Model DDM (4)'!D82 -> 4200 | G6: Sumber: harga penutupan pasar
B7: Nilai Intrinsik (Blended 3 Metode) | C7: ='Financial Model DDM (4)'!D81 -> 5632.4138 | G7: ="Bobot: DDM 2-Stage "&TEXT('Financial Model DDM (4)'!E78,"0%")&" | P/BV "&TEXT('Financial Model DDM (4)'!E79,"0%")&" | P/E "&TEXT('Financial Model DDM (4)'!E80,"0%") -> Bobot: DDM 2-Stage 20% | P/BV 60% | P/E 20%
B8: Potensial Upside | C8: =C7/C6-1 -> 0.34105092
B9: Rekomendasi | C9: =IF(C8>=0.2,"BUY",IF(C8>=0.05,"ACCUMULATE",IF(C8>=-0.05,"HOLD","SELL"))) -> BUY | G9: Ambang: >=+20% BUY | >=+5% ACCUMULATE | >=-5% HOLD | sisanya SELL
B11: 2. ASUMSI KUNCI | C11: Nilai | G11: Sumber / Dasar
B12: Risk Free Rate (Rf) | C12: ='Financial Model DDM (4)'!D6 -> 0.07 | G12: Yield SBN 10 tahun (benchmark)
B13: Beta | C13: ='Financial Model DDM (4)'!D7 -> 0.76 | G13: Damodaran
B14: Equity Risk Premium (Rm - Rf) | C14: ='Financial Model DDM (4)'!D8 -> 0.0669 | G14: Damodaran
B15: Cost of Equity (r) = Rf + Beta x ERP | C15: ='Financial Model DDM (4)'!D9 -> 0.120844 | G15: CAPM
B16: Pertumbuhan Pendapatan 2026 | C16: ='Financial Model DDM (4)'!G12 -> -0.11026109 | G16: OUTPUT, bukan asumsi - dihitung dari build-up H1 2026 aktual. Mencerminkan dekonsolidasi BSI.
B17: Pertumbuhan Pendapatan 2027-2030 | C17: ='Financial Model DDM (4)'!H12 -> 0.06 | G17: Input. Di bawah PDB nominal Indonesia (~7-8%), konservatif.
B18: Tarif PPh Badan | C18: ='Financial Model DDM (4)'!D16 -> 0.19 | G18: Tarif Tbk free float >=40% (PP 30/2020, UU 7/2021). Realisasi 19,0-19,9%, bukan statutori 22%.
B19: Hak Minoritas (% Laba Bersih) 2026-2030 | C19: ='Financial Model DDM (4)'!G18 -> 0.038407 | G19: ="Estimasi pasca-dekonsolidasi BSI (lapkeu interim Q2 2026). Historis "&TEXT('Financial Model DDM (4)'!D18,"0.0%")&" / "&TEXT('Financial Model DDM (4)'!E18,"0.0%")&" / "&TEXT('Financial Model DDM (4)'!F18,"0.0%")&", mayoritas dari minoritas BSI." -> Estimasi pasca-dekonsolidasi BSI (lapkeu interim Q2 2026). Historis 8.3% / 8.8% / 8.2%, mayoritas dari minoritas BSI.
B20: Dividend Payout Ratio Jangka Panjang | C20: ='Financial Model DDM (4)'!D19 -> 0.7 | G20: Kebijakan 60-70%. Historis aktual: 60% / 78% / 79%.
B21: g Terminal (perpetuitas) | C21: ='Financial Model DDM (4)'!D53 -> 0.05 | G21: Proxy PDB nominal jangka panjang. Wajib di bawah SGR Terminal dan r - lihat bagian 5.
B23: 3. JEMBATAN NILAI - TWO-STAGE DDM | C23: Rp / saham | D23: % dari Nilai
B24: Stage 1: PV Dividen 2026-2030 (5 tahun eksplisit) | C24: ='Financial Model DDM (4)'!D62 -> 1825.7076 | D24: =C24/$C$27 -> 0.2744943 | G24: DAPAT DIVERIFIKASI - berasal dari proyeksi laba rugi; 2026 dari data aktual
B25: Terminal Value posisi akhir 2030 (belum didiskonto) | C25: ='Financial Model DDM (4)'!D64 -> 8536.1999 | G25: ="Implied terminal P/BV "&TEXT(C25/'Financial Model DDM (4)'!K44,"0.00")&"x vs rata-rata peers "&TEXT('Financial Model DDM (4)'!D73,"0.00")&"x - cek silang kewajaran g" -> Implied terminal P/BV 2.03x vs rata-rata peers 1.75x - cek silang kewajaran g
B26: Stage 2: PV Terminal Value (2031 s.d. selamanya) | C26: ='Financial Model DDM (4)'!D65 -> 4825.46 | D26: =C26/$C$27 -> 0.7255057 | G26: TIDAK DAPAT DIVERIFIKASI - berasal dari asumsi g abadi
B27: NILAI INTRINSIK DDM (Stage 1 + Stage 2) | C27: ='Financial Model DDM (4)'!D66 -> 6651.1676 | D27: =C24/C27+C26/C27 -> 1
B28: Pembanding: Gordon 1-Tahap (g berlaku sejak 2026) | C28: ='Financial Model DDM (4)'!D55 -> 6439.0248 | G28: Struktur alternatif; selisihnya = nilai pertumbuhan 2027-2030
B30: 4. RINGKASAN METODE & BOBOT | C30: Nilai Wajar | D30: Bobot | E30: Kontribusi
B31: Income Approach - DDM 2-Stage | C31: ='Financial Model DDM (4)'!D78 -> 6651.1676 | D31: ='Financial Model DDM (4)'!E78 -> 0.2 | E31: =C31*D31 -> 1330.2335 | G31: Menangkap kemampuan bayar dividen jangka panjang
B32: Market Approach - P/BV Peers | C32: ='Financial Model DDM (4)'!D79 -> 5325.936 | D32: ='Financial Model DDM (4)'!E79 -> 0.6 | E32: =C32*D32 -> 3195.5616 | G32: ="Rata-rata P/BV peers "&TEXT('Financial Model DDM (4)'!D73,"0.00")&"x x BVPS 2025 "&TEXT('Financial Model DDM (4)'!D74,"#,##0") -> Rata-rata P/BV peers 1.75x x BVPS 2025 3,049
B33: Market Approach - P/E Peers | C33: ='Financial Model DDM (4)'!D80 -> 5533.0936 | D33: ='Financial Model DDM (4)'!E80 -> 0.2 | E33: =C33*D33 -> 1106.6187 | G33: ="Rata-rata P/E peers "&TEXT('Financial Model DDM (4)'!E73,"0.00")&"x x EPS 2025 "&TEXT('Financial Model DDM (4)'!E74,"#,##0") -> Rata-rata P/E peers 9.17x x EPS 2025 603
B34: BLENDED INTRINSIC VALUE | D34: =SUM(D31:D33) -> 1 | E34: =SUM(E31:E33) -> 5632.4138
B35: Harga Pasar | E35: =$C$6 -> 4200
B36: SAFETY ROOM / UPSIDE | E36: =E34/E35-1 -> 0.34105092
B38: 5. UJI KELAYAKAN ASUMSI g | C38: Nilai
B39: ROE Terminal (2030) | C39: ='Financial Model DDM (4)'!D50 -> 0.19541644 | G39: Memakai ekuitas akhir tahun, bukan rata-rata
B40: Retention Ratio (1 - DPR) | C40: ='Financial Model DDM (4)'!D51 -> 0.3
B41: SGR Terminal = ROE x Retention (batas atas g) | C41: ='Financial Model DDM (4)'!D52 -> 0.058624933 | G41: Pertumbuhan maksimum yang dapat didanai laba ditahan tanpa modal baru
B42: g Terminal yang dipakai | C42: =$C$21 -> 0.05
B43: Bantalan (SGR - g) | C43: =C41-C42 -> 0.0086249327
B44: Cost of Equity (batas atas kedua) | C44: =$C$15 -> 0.120844 | G44: g wajib < r, jika tidak rumus perpetuitas tidak sah
B45: Status | C45: ='Financial Model DDM (4)'!D56 -> OK | G45: Syarat: g < SGR Terminal DAN g < r
B47: 6. RENTANG SENSITIVITAS (r vs g) - 7 nilai r x 7 nilai g = 49 skenario | C47: Nilai | D47: Upside
B48: Sudut pesimis (r tertinggi + g terendah) | C48: ='Financial Model DDM (4)'!D136 -> 5278.9519 | D48: =C48/$C$6-1 -> 0.25689332 | G48: ="Setara beta "&TEXT(MAX('Financial Model DDM (4)'!B128:B134),"0.00")&" (vs "&TEXT($C$13,"0.00")&" dipakai) dengan g "&TEXT(MIN('Financial Model DDM (4)'!D127:J127),"0.0%") -> Setara beta 0.98 (vs 0.76 dipakai) dengan g 3.5%
B49: Base case (model) | C49: ='Financial Model DDM (4)'!G131 -> 5632.4138 | D49: =C49/$C$6-1 -> 0.34105092 | G49: Sel tengah tabel 7x7; harus sama dengan Nilai Intrinsik di bagian 1
B50: Sudut optimis (r terendah + g tertinggi yang sah) | C50: ='Financial Model DDM (4)'!D137 -> 6127.1605 | D50: =C50/$C$6-1 -> 0.45884774 | G50: Hanya kolom dengan g < SGR Terminal yang dihitung
B51: Kesimpulan di semua 49 skenario | C51: ='Financial Model DDM (4)'!D138 -> BERTAHAN di semua 49 skenario | G51: Tabel lengkap 7 x 7 = 49 skenario ada di Financial Model DDM (4) baris 126-138, lengkap dengan kolom Implied Beta
B52: Kontribusi Terminal Value | C52: ='Financial Model DDM (4)'!D67 -> 0.7255057 | G52: Bagian nilai yang bergantung asumsi g abadi - gunakan rentang, bukan angka tunggal
B54: 7. DASAR PROYEKSI 2026 - DATA AKTUAL H1 2026 | C54: H1 2026 | D54: H1 2025 | E54: Perubahan | G54: Keterangan
B55: Pendapatan (Rp miliar) | C55: ='Financial Model DDM (4)'!K86 -> 73387 | D55: ='Financial Model DDM (4)'!J86 -> 81638 | E55: =C55/D55-1 -> -0.10106813 | G55: Turun terutama karena dekonsolidasi BSI (efektif 1 Feb 2026)
B56: Beban Usaha (Rp miliar) | C56: =-'Financial Model DDM (4)'!K89 -> 9268 | D56: =-'Financial Model DDM (4)'!J89 -> 19001 | E56: =C56/D56-1 -> -0.5122362 | G56: Penghematan beban = sumber kenaikan laba meski pendapatan turun
B57: Laba Bersih (Rp miliar) | C57: ='Financial Model DDM (4)'!K94 -> 31626 | D57: ='Financial Model DDM (4)'!J94 -> 26852 | E57: =C57/D57-1 -> 0.17778936
B58: Cost-to-Income (Beban Usaha / Laba Kotor) | C58: ='Financial Model DDM (4)'!K101 -> 0.19176098 | D58: ='Financial Model DDM (4)'!J101 -> 0.36229646 | E58: =C58-D58 -> -0.17053548 | G58: Perubahan dalam poin persentase
B59: Tarif Pajak Efektif | C59: ='Financial Model DDM (4)'!K102 -> 0.18992854 | D59: ='Financial Model DDM (4)'!J102 -> 0.19906938 | E59: =C59-D59 -> -0.0091408423 | G59: Mendukung asumsi tarif 19% (bukan 22%)
B60: Laba Bersih FY2026 (H1 aktual + H2 proyeksi, Rp miliar) | C60: ='Financial Model DDM (4)'!F121 -> 63249.21 | G60: H2 = H1 x (1 + pertumbuhan H2), BPP & beban usaha mengikuti H1 aktual
B61: EPS 2026 (Rp) | C61: ='Financial Model DDM (4)'!G39 -> 651.66611 | G61: Laba atribusi / 93,33 miliar lembar
B62: DPS 2026 (Rp) = D1 untuk DDM | C62: ='Financial Model DDM (4)'!G40 -> 456.16627 | G62: ="DPR "&TEXT('Financial Model DDM (4)'!D19,"0%")&" x EPS 2026" -> DPR 70% x EPS 2026
B63: Cek build-up FY2026 | C63: ='Financial Model DDM (4)'!D123 -> OK - build-up = laporan laba rugi | G63: Laba bersih build-up harus sama dengan laporan laba rugi 2026
